perceptual_manifold_geometry/__init__.py
perceptual_manifold_geometry/curvature.py
perceptual_manifold_geometry/density.py
perceptual_manifold_geometry/holes.py
perceptual_manifold_geometry/intrinsic_dimension.py
perceptual_manifold_geometry/nonconvexity.py
perceptual_manifold_geometry-0.1.4.dist-info/METADATA
perceptual_manifold_geometry-0.1.4.dist-info/WHEEL
perceptual_manifold_geometry-0.1.4.dist-info/top_level.txt
perceptual_manifold_geometry-0.1.4.dist-info/RECORD
