Metadata-Version: 2.1
Name: perceptual-manifold-geometry
Version: 0.1.4
Summary: A package for analyzing the geometry of perceptual manifolds
Home-page: https://github.com/mayanbiao1234/Geometric-metrics-for-perceptual-manifolds
Author: Yanbiao Ma
Author-email: ybmamail@stu.xidian.edu.cn
Classifier: Programming Language :: Python :: 3
Classifier: License :: OSI Approved :: MIT License
Classifier: Operating System :: OS Independent
Requires-Python: >=3.6
Requires-Dist: numpy
Requires-Dist: scikit-learn
Requires-Dist: scipy
Requires-Dist: ripser
Requires-Dist: persim
Requires-Dist: matplotlib
Requires-Dist: scikit-dimension
